lab_data_logger/__init__.py
lab_data_logger/_version.py
lab_data_logger/cli.py
lab_data_logger/logger.py
lab_data_logger/services.py
lab_data_logger/utils.py
lab_data_logger-0.5.2.dist-info/LICENSE
lab_data_logger-0.5.2.dist-info/METADATA
lab_data_logger-0.5.2.dist-info/WHEEL
lab_data_logger-0.5.2.dist-info/entry_points.txt
lab_data_logger-0.5.2.dist-info/top_level.txt
lab_data_logger-0.5.2.dist-info/RECORD
