Metadata-Version: 2.1
Name: lab-data-logger
Version: 0.5.2
Summary: A (distributed) data logger for the (physics) lab.
Home-page: https://github.com/bleykauf/lab_data_logger
Author: Bastian Leykauf
Author-email: leykauf@physik.hu-berlin.de
Maintainer: Bastian Leykauf
Maintainer-email: leykauf@physik.hu-berlin.de
License: UNKNOWN
Platform: UNKNOWN
Classifier: Programming Language :: Python :: 3
Classifier: License :: OSI Approved :: GNU General Public License v3 (GPLv3)
Classifier: Operating System :: POSIX :: Linux
Classifier: Intended Audience :: Science/Research
Requires-Python: >=3.5
Requires-Dist: click
Requires-Dist: click-log
Requires-Dist: rpyc
Requires-Dist: influxdb
